[
    {
        "classes": [
            {
                "className": "paintball",
                "lineNumber": 6,
                "object": true,
                "qualifiedClassName": "paintball",
                "superClasses": [
                    {
                        "access": "public",
                        "name": "QQuickPaintedItem"
                    }
                ]
            }
        ],
        "inputFile": "paintball.h",
        "outputRevision": 68
    },
    {
        "classes": [
            {
                "className": "view",
                "lineNumber": 10,
                "methods": [
                    {
                        "access": "public",
                        "index": 0,
                        "name": "initialize",
                        "returnType": "void"
                    }
                ],
                "object": true,
                "qualifiedClassName": "view",
                "superClasses": [
                    {
                        "access": "public",
                        "name": "QQuickItem"
                    }
                ]
            }
        ],
        "inputFile": "view.h",
        "outputRevision": 68
    }
]
